{
    "fabric:load_conditions": [
        {
            "condition": "fabric:all_mods_loaded",
            "values": [
                "farmersdelight"
            ]
        },
        {
            "condition": "fabric:tags_populated",
            "values": [
                "c:sausage_fish_pizza"
            ]
        }
    ],
    "type": "farmersdelight:cutting",
    "ingredients": [
        {
            "tag": "c:sausage_fish_pizza"
        }
    ],
    "tool": {
        "tag": "c:tools/knives"
    },
    "result": [
        {
            "count": 4,
            "item": "createfood:sausage_fish_pizza_slice"
        }
    ]
}