{
    "fabric:load_conditions": [
        {
            "condition": "fabric:all_mods_loaded",
            "values": [
                "farmersdelight"
            ]
        },
        {
            "condition": "fabric:tags_populated",
            "values": [
                "c:dark_chocolate_bottle",
                "c:hot_dark_chocolate_bottle"
            ]
        }
    ],
    "type": "farmersdelight:cooking",
    "cookingtime": 25,
    "experience": 0.25,
    "ingredients": [
        {
            "tag": "c:dark_chocolate_bottle"
        }
    ],
    "result": {
        "item": "createfood:hot_dark_chocolate_bottle"
    }
}